Workbook

Sheet Answers
C3: Questions | D3: Enter your answer here
B4: Problem 1 | C4: A | D4: ='1'!E20 -> 10
C5: B | D5: ='1'!E23 -> 0.22727273
C6: C | D6: ='1'!E26 -> -0.18181818
B8: Problem 2 | C8: A | D8: ='2'!D15 -> 3.2408009
C9: B | D9: ='2'!D19 -> 3.0301001
C10: C | D10: ='2'!D20 -> 0.29080089
B12: Problem 3 | C12: A | D12: ='3'!D16 -> 636.86561
C13: B | D13: ='3'!D18 -> 999.24452
B15: Problem 4 | C15: A | D15: ='4'!D22 -> 0.075962699
B17: Problem 5 | C17: A | D17: ='5'!D17 -> 0.015
C18: B | D18: ='5'!D18 -> 0.06
C19: C | D19: ='5'!D19 -> 0.12
C20: D | D20: ='5'!D21 -> The higher the PSA number, the faster people pay off their mortgages early. 50 PSA is slower, 200 PSA is faster, and 400 PSA is the fastest. | E20: *enter interpretation here
B22: Problem 6 | C22: A | D22: ='6'!D16 -> 9.2
C23: B | D23: ='6'!D18 -> 8.556
C24: C | D24: ='6'!D20 -> 51336
C25: D | D25: ='6'!D22 -> -8664
G28: Enter your answer here (simply copy from the answers in tab 7).
E29: Problem 7 | F29: A | G29: The manager is right, but the claim is misleading. Investing in equities for a long time is likely to reduce the probability of a loss because good years may offset bad years. However, this does not mean equities are less risky. The problem is that the manager is mistakenly equating a " lower chance of loss " with " lower total risk ". A 30-year investor may have lower yearly risk because the average return per year is more steady. But the final wealth (total return) at the end of 30 years can still be very volatile because the investment has more time to fluctuate up and down. Therefore a 30-year investor has lower annual risk, but not lower total wealth volatility than a 1-year investor.
F30: B | G30: PE returns can appear less risky than they actually are because the value of PE funds is not updated daily like public stocks. They are typically priced quarterly, based on estimates. This means losses may be shown slowly, not right away. This "smoothing" can make PE returns appear stable even when stock markets are declining. This reduces volatility and increases the Sharpe ratio, making PE seem like it offers high return with low risk. This can confuse allocation models into investing too much in PE. Secondary market prices can be more accurate because they reflect the prices that buyers are willing to pay. However, they are not completely accurate because prices can be lower when demand is low or when sellers need cash quickly.
F31: C | G31: The analyst is wrong because an MBS is not as risky as a Treasury bond. A Treasury bond has fixed cash flows, so investors know when they will be paid. An MBS is different because homeowners can choose to pay off their mortgages early. This is known as a prepayment option. When interest rates go down, homeowners tend to refinance their mortgages, so the MBS investors get their money back earlier and have to invest it at a lower rate. When interest rates increase, homeowners do not refinance as much, so the investors are stuck in the MBS for longer. This means the MBS becomes shorter when interest rates fall and longer when they rise. Because of this, an MBS has more uncertain cash flows and different price sensitivity than a Treasury bond, even if their coupons and maturities are the same.
F32: D | G32: The student is wrong because a 2× leveraged ETF is supposed to return twice the daily return, not twice the yearly return. This is important because the ETF resets every day, so the outcome depends on daily returns. When the market is very volatile, the ETF could lose value even if the index ends up close to where it began. This is because it is harder to recover from a loss than to make a profit. Because the ETF leverages gains and losses, volatility can reduce the long-term return. Therefore, the ETF might not be twice the index return after one year.

Sheet 1
C4: Input Area:
I6: You have decided to purchase 25 oil futures contracts at a settle price of $55 per barrel.
C7: Settle price | D7: 55 | I7: Each futures contract has a standard size of 1,000 barrels and an initial margin requirement of $5,500.
C8: Contract size | D8: 1000 | E8: barrels
C9: Margin | D9: 5500 | I9: a. What is the leverage factor associated with these contracts?
C10: Number of contracts | D10: 25 | I10: b. If oil rises to $56.25 per barrel, what is the total percentage return on your futures position?
I11: c. What is the total percentage return on your futures position if oil falls to $54 per barrel?
C12: New price of oil | D12: 56.25
C13: New price of oil | D13: 54
C16: Output Area:
C19: Initial margin in percent | E19: =D9/(D7*D8) -> 0.1 | F19: D9/(D7*D8)
C20: Leverage factor | E20: =(D7*D8)/D9 -> 10 | F20: (D7*D8)/D9 | H20: A
C22: Cash return on oil | E22: =(D12-D7)/D7 -> 0.022727273 | F22: (D12-D7)/D7
C23: Levered return | E23: =((D12-D7)*D8*D10)/(D9*D10) -> 0.22727273 | F23: ((D12-D7)*D8*D10)/(D9*D10) | H23: B
C25: Cash return on oil | E25: =(D13-D7)/D7 -> -0.018181818 | F25: (D13-D7)/D7
C26: Levered return | E26: =E25*$E$20 -> -0.18181818 | F26: E25*$E$20 | H26: C

Sheet 2
C1: Input Area:
I3: Suppose unleaded gasoline is currently trading at $3 per gallon.
C4: Unleaded spot price | D4: 3 | E4: per gallon | I4: You face an interest rate of 4 percent and a carrying cost of $.07 per gallon per month.
C5: Interest rate | D5: 0.04 | I5: The current market price of a specified duration futures contract on gasoline is $2.95 per gallon.
C6: Carry cost per gallon per month | D6: 0.07 | I6: You are evaluating a three-month carry trade opportunity.
C7: Contract length | D7: 3 | E7: months | I7: a. Determine the present value of the storage costs (PVSC).
C8: Futures price | D8: 2.95 | I8: b. Identify what the futures price should be under spot-futures parity.
I9: c. Explain the trades necessary to conduct the carry trade and calculate the potential profit per gallon.
C11: Output Area:
C14: PV of storage costs | D14: =PV($D$5/12,$D$7,-$D$6,0,0) -> 0.20860774 | F14: PV($D$5/12,$D$7,-$D$6,0,0)
C15: Six month F price should be | D15: =($D$4+D14)*(1+$D$5/12)^$D$7 -> 3.2408009 | E15: A | F15: ($D$4+D14)*(1+$D$5/12)^$D$7
C16: Decision | D16: =IF($D$8<D15,"Buy futures",IF($D$8>D15,"Sell futures","No arbitrage")) -> Buy futures
C19: FV of investment | D19: =$D$4*(1+$D$5/12)^$D$7 -> 3.0301001 | E19: B | F19: $D$4*(1+$D$5/12)^$D$7
C20: Arbitrage profit per gallon | D20: =ABS(D15-$D$8) -> 0.29080089 | E20: C | F20: ABS(D15-$D$8)

Sheet 3
C4: Input Area:
G6: A 20-year mortgage has an annual interest rate of 4.9 percent
C7: # of years | D7: 20 | G7: and a loan amount of $250,000.
C8: Original balance | D8: 250000 | G8: What are the interest and principal for the 120th payment?
C9: Rate | D9: 0.049
C10: Payment number | D10: 120
C13: Output Area:
C16: Interest | D16: =IPMT($D$9/12,$D$10,$D$7*12,-$D$8) -> 636.86561 | E16: IPMT($D$9/12,$D$10,$D$7*12,-$D$8) | F16: A
C18: Principal | D18: =PPMT($D$9/12,$D$10,$D$7*12,-$D$8) -> 999.24452 | E18: PPMT($D$9/12,$D$10,$D$7*12,-$D$8) | F18: B

Sheet 4
C3: Input Area:
G5: A homeowner took out a 30-year fixed-rate mortgage of $120,000.
C6: Loan amount | D6: 120000 | G6: The mortgage was taken out 15 years ago at a rate of 7.95 percent. If the homeowner refinances,
C7: # of years | D7: 30 | G7: the charges will be $2,000. What is the highest interest rate at which it would be beneficial
C8: # of years left at payoff | D8: 15 | G8: to refinance the mortgage?
C9: Rate | D9: 0.0795
C10: Refinance charges | D10: 2000
C13: Output Area:
C16: Monthly payment | D16: =PMT($D$9/12,$D$7*12,-$D$6) -> 876.33837 | E16: PMT($D$9/12,$D$7*12,-$D$6)
C18: Mortgage balance | D18: =PV($D$9/12,$D$8*12,-D16) -> 91978.165 | E18: PV($D$9/12,$D$8*12,-D16)
C20: Amount to borrow | D20: =D18+$D$10 -> 93978.165 | E20: D18+$D$10
C22: New interest rate | D22: =RATE($D$8*12,-D16,D20)*12 -> 0.075962699 | E22: RATE($D$8*12,-D16,D20)*12 | F22: A
C23: Anything below this rate will result in | D23: Refinancing is beneficial only if the new rate is below 7.60%, because it lowers total borrowing cost.
C24: lower mortgage payments.

Sheet 5
C2: Input Area:
G6: What are the conditional prepayment rates for seasoned 50 PSA, 200 PSA,
C7: PSA 100 | D7: 0.03 | G7: and 400 PSA mortgages if the 100 PSA benchmark is 3 percent per year?
C8: PSA | D8: 50 | G8: How do you interpret these numbers?
C9: PSA | D9: 200
C10: PSA | D10: 400
C13: Output Area:
C16: PSA | D16: CPR
C17: =D8 -> 50 | D17: =$D$7*(C17/100) -> 0.015 | E17: $D$7*(C17/100) | F17: A
C18: =D9 -> 200 | D18: =$D$7*(C18/100) -> 0.06 | E18: $D$7*(C18/100) | F18: B
C19: =D10 -> 400 | D19: =$D$7*(C19/100) -> 0.12 | E19: $D$7*(C19/100) | F19: C
D21: The higher the PSA number, the faster people pay off their mortgages early. 50 PSA is slower, 200 PSA is faster, and 400 PSA is the fastest. | F21: D
D22: *enter interpretation here

Sheet 6
C3: Suppose you purchase 6,000 shares of a closed-end mutual fund at its initial public offering; the offer price is $10 per share. The offering prospectus discloses that the fund promoter gets an 8 percent fee from the offering. If this fund sells at a 7 percent discount to NAV the day after the initial public offering, what is the value of your investment?
C5: Input Area:
C7: # of shares | D7: 6000
C8: Price per share | D8: 10
C9: Promoter fee | D9: 0.08
C10: Fund discount | D10: 0.07
C13: Output Area:
C16: NAV @ IPO | D16: =$D$8*(1-$D$9) -> 9.2 | F16: A | G16: $D$8*(1-$D$9)
C18: Share price | D18: =D16*(1-$D$10) -> 8.556 | F18: B | G18: D16*(1-$D$10)
C20: Value of investment | D20: =$D$7*D18 -> 51336 | F20: C | G20: $D$7*D18
C22: Gain/loss | D22: =D20-($D$7*$D$8) -> -8664 | F22: D | G22: D20-($D$7*$D$8)

Sheet 7
C3: Question A
C5: A portfolio manager claims that investing in equities for longer periods makes them “less risky,” because “time diversification reduces the chance of loss.” Using the data pattern described in the Fallacy of Time Diversification section, critically evaluate this claim. Then, derive whether a 30-year equity investor faces lower risk per year or lower total wealth volatility than a 1-year investor. Finally, propose an alternative argument — consistent with portfolio theory — explaining why younger investors may still hold more equities despite this fallacy.
C8: A
C9: The manager is right, but the claim is misleading. Investing in equities for a long time is likely to reduce the probability of a loss because good years may offset bad years. However, this does not mean equities are less risky. The problem is that the manager is mistakenly equating a " lower chance of loss " with " lower total risk ". A 30-year investor may have lower yearly risk because the average return per year is more steady. But the final wealth (total return) at the end of 30 years can still be very volatile because the investment has more time to fluctuate up and down. Therefore a 30-year investor has lower annual risk, but not lower total wealth volatility than a 1-year investor.
C17: Question B
C19: Private equity (PE) funds report quarterly valuations based on internal models, often using “smoothing” adjustments for unrealized gains and losses. Assume you are evaluating a university endowment that reports stable, upward-trending returns from its PE portfolio—even during public market downturns.
C20: Explain how valuation smoothing and infrequent pricing can create the illusion of low volatility and high Sharpe ratios in PE fund performance. Discuss why this illusion can mislead institutional portfolio allocation models that rely on mean–variance optimization. Critically evaluate whether secondary market pricing (LP share resale markets) provides a better proxy for true PE volatility, and explain the trade-offs in using it.
C23: B
C24: PE returns can appear less risky than they actually are because the value of PE funds is not updated daily like public stocks. They are typically priced quarterly, based on estimates. This means losses may be shown slowly, not right away. This "smoothing" can make PE returns appear stable even when stock markets are declining. This reduces volatility and increases the Sharpe ratio, making PE seem like it offers high return with low risk. This can confuse allocation models into investing too much in PE. Secondary market prices can be more accurate because they reflect the prices that buyers are willing to pay. However, they are not completely accurate because prices can be lower when demand is low or when sellers need cash quickly.
C32: Question C
C34: A 30-year fixed-rate mortgage-backed security (MBS) and a 30-year Treasury bond have identical coupon rates and maturities. An analyst claims they should therefore exhibit nearly identical price sensitivity to interest-rate changes. Explain why this statement is fundamentally flawed, focusing on the embedded options, duration asymmetry, and investor cash-flow risk.
C40: C
... C56: The student is wrong because a 2× leveraged ETF is supposed to return twice the daily return, not twice the yearly return. This is important because the ETF resets every day, so the outcome depends on daily returns. When the market is very volatile, the ETF could lose value even if the index ends up close to where it began. This is because it is harder to recover from a loss than to make a profit. Because the ETF leverages gains and losses, volatility can reduce the long-term return. Therefore, the ETF might not be twice the index return after one year.
